scrapy_selenium_customdriverinstance/__init__.py
scrapy_selenium_customdriverinstance/http.py
scrapy_selenium_customdriverinstance/middlewares.py
scrapy_selenium_customdriverinstance-0.0.1.dist-info/LICENCE
scrapy_selenium_customdriverinstance-0.0.1.dist-info/METADATA
scrapy_selenium_customdriverinstance-0.0.1.dist-info/WHEEL
scrapy_selenium_customdriverinstance-0.0.1.dist-info/top_level.txt
scrapy_selenium_customdriverinstance-0.0.1.dist-info/RECORD
