Metadata-Version: 2.1
Name: scrapy-selenium-customdriverinstance
Version: 0.0.1
Summary: A small example package
Author-email: Lucio Montero <lucioric2000@hotmail.com>
Project-URL: Homepage, https://github.com/pypa/sampleproject
Project-URL: Issues, https://github.com/pypa/sampleproject/issues
Classifier: Programming Language :: Python :: 3
Classifier: License :: Free To Use But Restricted
Classifier: Operating System :: OS Independent
Requires-Python: >=3.8
License-File: LICENCE
